MANIFEST.in
README.md
setup.py
farmpy/__init__.py
farmpy/lsf.py
farmpy/lsf_stats.py
farmpy/tasks.py
farmpy.egg-info/PKG-INFO
farmpy.egg-info/SOURCES.txt
farmpy.egg-info/dependency_links.txt
farmpy.egg-info/requires.txt
farmpy.egg-info/top_level.txt
farmpy/tests/lsf_stats_test.py
farmpy/tests/lsf_test.py
farmpy/tests/tasks_test.py
farmpy/tests/data/lsf_unittest_lsadmin_showconf_bad_units.txt
farmpy/tests/data/lsf_unittest_lsadmin_showconf_kb.txt
farmpy/tests/data/lsf_unittest_lsadmin_showconf_mb.txt
farmpy/tests/data/lsf_unittest_lsadmin_showconf_no_units.txt
farmpy/tests/data/lsf_unittest_outfile
farmpy/tests/data/lsf_unittest_outfile2
farmpy/tests/data/lsf_unittest_run_bsub_fails.sh
farmpy/tests/data/lsf_unittest_run_bsub_ok.sh
farmpy/tests/data/lsf_unittest_run_not_bsubbed.out
farmpy/tests/data/lsf_unittest_run_not_bsubbed_array.out
scripts/bsub.py
scripts/bsub_out_to_stats