Metadata-Version: 1.0
Name: farmpy
Version: 0.42.0
Summary: Package to run farm jobs - currently LSF supported
Home-page: https://github.com/martinghunt/farmpy
Author: Martin Hunt
Author-email: mh12@sanger.ac.uk
License: GPL
Platform: UNKNOWN
